migrations/__init__.py
new_plugin/__init__.py
new_plugin/admin.py
new_plugin/apps.py
new_plugin/forms.py
new_plugin/urls.py
new_plugin/views.py
new_plugin-0.0.2.dist-info/METADATA
new_plugin-0.0.2.dist-info/WHEEL
new_plugin-0.0.2.dist-info/entry_points.txt
new_plugin-0.0.2.dist-info/top_level.txt
new_plugin-0.0.2.dist-info/RECORD
