Metadata-Version: 2.1
Name: new-plugin
Version: 0.0.2
Summary: LOL KEK CHEBUREK
Home-page: UNKNOWN
License: UNKNOWN
Platform: UNKNOWN
